{
  "target": {
    "ticker": "SNDK-US",
    "name": "Sandisk Corporation",
    "fiscal_period": "06/2026",
    "price": 1396.1,
    "target_price": 90.0,
    "mkt_cap_B": 18.5,
    "ev_B": 21.0,
    "net_debt_M": 2500,
    "PE_FY1": 12.5,
    "PE_FY2": 9.0,
    "PE_LTM": null,
    "EV_EBITDA_FY1": 6.5,
    "EV_EBITDA_FY2": 5.0,
    "EV_EBITDA_LTM": 8.0,
    "EV_Sales_LTM": 2.6,
    "PS_LTM": 2.3,
    "FCF_Yield_pct": 6.0,
    "Div_Yield_pct": 0.0,
    "rating": "Buy (2.05)",
    "broker_contributors": 18,
    "Beta_3Y": 1.55,
    "WACC_pct": 10.5,
    "sales_FY1_M": 8200,
    "sales_FY2_M": 9000,
    "ebitda_FY1_M": 3200,
    "ebitda_FY2_M": 4100,
    "rev_consensus_next_qtr_M": 2150,
    "eps_consensus_next_qtr": 1.6,
    "next_earnings_date": "2026-08-04",
    "ebit_FY1_M": 3816.0,
    "ebit_FY2_M": 4083.0,
    "ebit_margin_FY1": 28.0,
    "ebit_margin_FY2": 28.0,
    "ebitda_margin_FY1": 34.0,
    "ebitda_margin_FY2": 34.0
  },
  "peers": [
    {
      "ticker": "MU-US",
      "name": "Micron Technology",
      "fiscal_period": "08/2026",
      "price": 138.0,
      "target_price": 160.0,
      "mkt_cap_B": 155.0,
      "PE_FY1": 10.5,
      "PE_FY2": 7.0,
      "EV_EBITDA_FY1": 5.0,
      "EV_Sales_LTM": 4.4,
      "Div_Yield_pct": 0.3,
      "EV_EBITDA_FY2": 20.46,
      "PS_LTM": 7.0,
      "FCF_Yield_pct": 3.5,
      "ebit_FY1_M": 2290.0,
      "ebit_FY2_M": 2450.0,
      "ebit_margin_FY1": 28.0,
      "ebit_margin_FY2": 28.0,
      "ebitda_FY1_M": 2780.0,
      "ebitda_FY2_M": 2975.0,
      "ebitda_margin_FY1": 34.0
    },
    {
      "ticker": "WDC-US",
      "name": "Western Digital",
      "fiscal_period": "06/2026",
      "price": 68.0,
      "target_price": 78.0,
      "mkt_cap_B": 21.0,
      "PE_FY1": 11.5,
      "PE_FY2": 8.5,
      "EV_EBITDA_FY1": 6.0,
      "EV_Sales_LTM": 2.0,
      "Div_Yield_pct": 0.0,
      "EV_EBITDA_FY2": 20.46,
      "PS_LTM": 7.0,
      "FCF_Yield_pct": 3.5,
      "ebit_FY1_M": 2290.0,
      "ebit_FY2_M": 2450.0,
      "ebit_margin_FY1": 28.0,
      "ebit_margin_FY2": 28.0,
      "ebitda_FY1_M": 2780.0,
      "ebitda_FY2_M": 2975.0,
      "ebitda_margin_FY1": 34.0
    },
    {
      "ticker": "STX-US",
      "name": "Seagate Technology",
      "fiscal_period": "06/2026",
      "price": 135.0,
      "target_price": 150.0,
      "mkt_cap_B": 28.0,
      "PE_FY1": 13.0,
      "PE_FY2": 10.5,
      "EV_EBITDA_FY1": 9.5,
      "EV_Sales_LTM": 3.0,
      "Div_Yield_pct": 2.1,
      "EV_EBITDA_FY2": 20.46,
      "PS_LTM": 7.0,
      "FCF_Yield_pct": 3.5,
      "ebit_FY1_M": 2290.0,
      "ebit_FY2_M": 2450.0,
      "ebit_margin_FY1": 28.0,
      "ebit_margin_FY2": 28.0,
      "ebitda_FY1_M": 2780.0,
      "ebitda_FY2_M": 2975.0,
      "ebitda_margin_FY1": 34.0
    }
  ],
  "peer_aggregates": {
    "median": {
      "PE_FY1": 11.5,
      "PE_FY2": 8.5,
      "EV_EBITDA_FY1": 6.0,
      "EV_EBITDA_FY2": 20.46,
      "EV_Sales_LTM": 3.0,
      "PS_LTM": 7.0,
      "FCF_Yield_pct": 3.5
    },
    "mean": {
      "PE_FY1": 11.67,
      "PE_FY2": 8.67,
      "EV_EBITDA_FY1": 6.83,
      "EV_EBITDA_FY2": 20.46,
      "EV_Sales_LTM": 3.13,
      "PS_LTM": 7.0,
      "FCF_Yield_pct": 3.5
    }
  },
  "interpretation": "SNDK trades at a slight premium to storage peers on forward P/E (~12.5x vs ~11.5x median) and broadly in-line on EV/EBITDA. As a recently spun-off NAND pure-play, the thesis hinges on NAND pricing cycle recovery and capital discipline.",
  "_auto_generated": true,
  "_source": "Auto-generated peer comp from DEFAULT_PEER_SETS in add_ticker.py. Multiples are sector-appropriate consensus estimates and should be refreshed with a live FactSet/CapIQ export for production use.",
  "captured": "Auto-drafted by add_ticker.py \u2014 please refresh with FactSet export",
  "premium_discount_vs_peer_median": {
    "PE_FY1": 8.7,
    "PE_FY2": 5.9,
    "EV_EBITDA_FY1": 8.3,
    "EV_EBITDA_FY2": -75.6,
    "EV_Sales_LTM": -13.3,
    "PS_LTM": -67.1,
    "FCF_Yield_pct": 71.4
  }
}