{
  "spot": 305.35,
  "spot_date": "2026-05-22",
  "sma20": 280.09,
  "sma50": 255.81,
  "sma100": 238.87,
  "sma200": 188.52,
  "rsi14": 67.55,
  "macd": 11.4734,
  "macd_signal": 11.1149,
  "macd_hist": 0.3585,
  "atr14": 9.52,
  "high_52w": 305.35,
  "low_52w": 80.79,
  "drawdown_from_52w_high_pct": 0.0,
  "pct_above_sma200_pct": 61.97,
  "pct_above_sma50_pct": 19.37,
  "sma50_above_sma200": true,
  "price_30d_change_pct": 14.030174023452101,
  "price_60d_change_pct": 44.29165485303847,
  "price_90d_change_pct": 27.724097544652217,
  "price_1y_change_pct": 268.824737287112,
  "open": 305.35,
  "high": 305.35,
  "low": 305.35,
  "plus_di": 67.55,
  "minus_di": 32.45,
  "adx14": 26.45,
  "bb_mid": 280.09,
  "bb_up": 317.28,
  "bb_lo": 242.89,
  "stoch_k": 100.0,
  "stoch_d": 94.45,
  "obv_latest": 6244.64,
  "obv_60d_change_M": 36.45,
  "obv_60d_pct_change_pct": 0.59,
  "volume_avg_30d_M": 9.27,
  "volume": 7.84,
  "high_52w_date": "2026-05-22",
  "low_52w_date": "2025-05-30",
  "last_cross_date": "2025-06-17"
}