{
  "as_of": "2026-05-11",
  "close": 151.5,
  "sma20": 144.994,
  "sma50": 155.566,
  "sma100": 177.737,
  "sma200": 205.1113,
  "atr14": 8.423478571428566,
  "atr_pct": 5.560051862329087,
  "adx14": 10.175857052724826,
  "plus_di": 25.765836378885584,
  "minus_di": 30.668000037163228,
  "rsi_14": 50.549084858569046,
  "realized_vol_30d_ann_pct": 72.95743848278914,
  "high_52w": 280.67,
  "low_52w": 118.3,
  "spot": 151.5,
  "spot_date": "2026-05-11",
  "open": 151.5,
  "high": 151.5,
  "low": 151.5,
  "sma50_above_sma200": false,
  "pct_above_sma50_pct": -2.62,
  "pct_above_sma200_pct": -26.14,
  "rsi14": 53.04,
  "bb_mid": 144.99,
  "bb_up": 156.38,
  "bb_lo": 133.61,
  "macd": -1.43,
  "macd_signal": -3.47,
  "macd_hist": 2.04,
  "stoch_k": 78.69,
  "stoch_d": 84.22,
  "obv_latest": 205.51,
  "obv_60d_change_M": -17.44,
  "obv_60d_pct_change_pct": -7.82,
  "volume_avg_30d_M": 7.85,
  "volume": 4.8,
  "high_52w_date": "2025-11-03",
  "low_52w_date": "2026-04-10",
  "drawdown_from_52w_high_pct": -45.33,
  "price_30d_change_pct": 25.09,
  "price_60d_change_pct": -15.57,
  "price_90d_change_pct": -13.9,
  "price_1y_change_pct": -12.92,
  "last_cross_date": "2026-02-06"
}